{"PUSH1": 550, "MSTORE": 189, "CALLVALUE": 1, "DUP1": 242, "ISZERO": 58, "PUSH2": 151, "JUMPI": 68, "REVERT": 31, "JUMPDEST": 130, "POP": 240, "CALLDATASIZE": 16, "LT": 24, "CALLDATALOAD": 40, "PUSH4": 25, "GT": 5, "EQ": 33, "JUMP": 65, "MLOAD": 86, "ADD": 236, "DUP3": 69, "DUP2": 250, "SUB": 76, "DUP4": 36, "SWAP2": 109, "SWAP1": 226, "DUP5": 23, "AND": 124, "EXP": 4, "NOT": 3, "SWAP3": 43, "RETURN": 14, "PUSH20": 114, "STOP": 8, "PUSH32": 36, "CALLER": 20, "SHA3": 44, "DUP6": 13, "SSTORE": 13, "LOG3": 5, "SLOAD": 25, "DUP7": 10, "SWAP4": 1, "MSIZE": 3, "CALLDATACOPY": 2, "LOG4": 2, "DUP11": 7, "DUP8": 2, "SWAP7": 1, "DUP10": 2, "SWAP5": 1, "GAS": 1, "STATICCALL": 1, "TIMESTAMP": 1, "DUP13": 1, "DUP12": 1, "DUP9": 1, "LOG2": 1, "PUSH6": 1, "PC": 1, "PUSH11": 1}